odoo10_addon_account_credit_control-10.0.1.4.6-nspkg.pth
odoo/addons/account_credit_control/README.rst
odoo/addons/account_credit_control/__init__.py
odoo/addons/account_credit_control/__manifest__.py
odoo/addons/account_credit_control/data/data.xml
odoo/addons/account_credit_control/i18n/account_credit_control.pot
odoo/addons/account_credit_control/i18n/am.po
odoo/addons/account_credit_control/i18n/ar.po
odoo/addons/account_credit_control/i18n/bg.po
odoo/addons/account_credit_control/i18n/bs.po
odoo/addons/account_credit_control/i18n/ca.po
odoo/addons/account_credit_control/i18n/ca_ES.po
odoo/addons/account_credit_control/i18n/cs.po
odoo/addons/account_credit_control/i18n/da.po
odoo/addons/account_credit_control/i18n/da_DK.po
odoo/addons/account_credit_control/i18n/de.po
odoo/addons/account_credit_control/i18n/el_GR.po
odoo/addons/account_credit_control/i18n/en_AU.po
odoo/addons/account_credit_control/i18n/en_GB.po
odoo/addons/account_credit_control/i18n/es.po
odoo/addons/account_credit_control/i18n/es_AR.po
odoo/addons/account_credit_control/i18n/es_CL.po
odoo/addons/account_credit_control/i18n/es_CO.po
odoo/addons/account_credit_control/i18n/es_CR.po
odoo/addons/account_credit_control/i18n/es_DO.po
odoo/addons/account_credit_control/i18n/es_EC.po
odoo/addons/account_credit_control/i18n/es_ES.po
odoo/addons/account_credit_control/i18n/es_MX.po
odoo/addons/account_credit_control/i18n/es_PE.po
odoo/addons/account_credit_control/i18n/es_PY.po
odoo/addons/account_credit_control/i18n/es_VE.po
odoo/addons/account_credit_control/i18n/et.po
odoo/addons/account_credit_control/i18n/eu.po
odoo/addons/account_credit_control/i18n/fa.po
odoo/addons/account_credit_control/i18n/fi.po
odoo/addons/account_credit_control/i18n/fr.po
odoo/addons/account_credit_control/i18n/fr_CA.po
odoo/addons/account_credit_control/i18n/fr_CH.po
odoo/addons/account_credit_control/i18n/fr_FR.po
odoo/addons/account_credit_control/i18n/gl.po
odoo/addons/account_credit_control/i18n/gl_ES.po
odoo10_addon_account_credit_control-10.0.1.4.6.dist-info/METADATA
odoo10_addon_account_credit_control-10.0.1.4.6.dist-info/WHEEL
odoo10_addon_account_credit_control-10.0.1.4.6.dist-info/namespace_packages.txt
odoo10_addon_account_credit_control-10.0.1.4.6.dist-info/top_level.txt
odoo10_addon_account_credit_control-10.0.1.4.6.dist-info/RECORD
