Metadata-Version: 2.1
Name: odoo10-addon-account-credit-control
Version: 10.0.1.4.6
Summary: Account Credit Control
Home-page: https://www.camptocamp.com
Author: Camptocamp,Odoo Community Association (OCA),Okia
Author-email: support@odoo-community.org
License: AGPL-3
Platform: UNKNOWN
Classifier: Programming Language :: Python
Classifier: Framework :: Odoo
Classifier: License :: OSI Approved :: GNU Affero General Public License v3
Requires-Python: ~=2.7
Requires-Dist: odoo (<10.1dev,>=10.0)
